{
  "name": "Field",
  "library": "terra-form",
  "display": "Field",
  "description": "Form layout container",
  "group": "Forms",
  "import_from": "terra-form/lib/Field",
  "properties": {
    "label": {
      "type": "String",
      "default": "Label"
    },
    "error": {
      "type": "String"
    },
    "help": {
      "type": "String"
    },
    "htmlFor": {
      "type": "String"
    },
    "isInline": {
      "type": "Bool",
      "display": "Inline"
    },
    "required": {
      "type": "Bool"
    },
    "children": {
      "type": "Array",
      "schema": {
        "type": "Component"
      }
    }
  }
}
